[
    {
        "Order": null,
        "job_id": 6,
        "op_id": 0,
        "machine_id": 0,
        "start_time": 0,
        "process_time": 97,
        "finish_time": 97,
        "job_type": null
    },
    {
        "Order": null,
        "job_id": 3,
        "op_id": 2,
        "machine_id": 0,
        "start_time": 97,
        "process_time": 96,
        "finish_time": 193,
        "job_type": null
    },
    {
        "Order": null,
        "job_id": 2,
        "op_id": 2,
        "machine_id": 0,
        "start_time": 193,
        "process_time": 43,
        "finish_time": 236,
        "job_type": null
    },
    {
        "Order": null,
        "job_id": 0,
        "op_id": 4,
        "machine_id": 0,
        "start_time": 236,
        "process_time": 76,
        "finish_time": 312,
        "job_type": null
    },
    {
        "Order": null,
        "job_id": 10,
        "op_id": 6,
        "machine_id": 0,
        "start_time": 312,
        "process_time": 85,
        "finish_time": 397,
        "job_type": null
    },
    {
        "Order": null,
        "job_id": 7,
        "op_id": 3,
        "machine_id": 0,
        "start_time": 397,
        "process_time": 61,
        "finish_time": 458,
        "job_type": null
    },
    {
        "Order": null,
        "job_id": 11,
        "op_id": 5,
        "machine_id": 0,
        "start_time": 463,
        "process_time": 17,
        "finish_time": 480,
        "job_type": null
    },
    {
        "Order": null,
        "job_id": 5,
        "op_id": 3,
        "machine_id": 0,
        "start_time": 490,
        "process_time": 79,
        "finish_time": 569,
        "job_type": null
    },
    {
        "Order": null,
        "job_id": 1,
        "op_id": 6,
        "machine_id": 0,
        "start_time": 569,
        "process_time": 43,
        "finish_time": 612,
        "job_type": null
    },
    {
        "Order": null,
        "job_id": 9,
        "op_id": 4,
        "machine_id": 0,
        "start_time": 612,
        "process_time": 32,
        "finish_time": 644,
        "job_type": null
    },
    {
        "Order": null,
        "job_id": 8,
        "op_id": 7,
        "machine_id": 0,
        "start_time": 644,
        "process_time": 60,
        "finish_time": 704,
        "job_type": null
    },
    {
        "Order": null,
        "job_id": 12,
        "op_id": 6,
        "machine_id": 0,
        "start_time": 705,
        "process_time": 19,
        "finish_time": 724,
        "job_type": null
    },
    {
        "Order": null,
        "job_id": 14,
        "op_id": 9,
        "machine_id": 0,
        "start_time": 905,
        "process_time": 48,
        "finish_time": 953,
        "job_type": null
    },
    {
        "Order": null,
        "job_id": 4,
        "op_id": 9,
        "machine_id": 0,
        "start_time": 959,
        "process_time": 7,
        "finish_time": 966,
        "job_type": null
    },
    {
        "Order": null,
        "job_id": 13,
        "op_id": 9,
        "machine_id": 0,
        "start_time": 969,
        "process_time": 8,
        "finish_time": 977,
        "job_type": null
    },
    {
        "Order": null,
        "job_id": 11,
        "op_id": 0,
        "machine_id": 1,
        "start_time": 0,
        "process_time": 85,
        "finish_time": 85,
        "job_type": null
    },
    {
        "Order": null,
        "job_id": 3,
        "op_id": 1,
        "machine_id": 1,
        "start_time": 85,
        "process_time": 8,
        "finish_time": 93,
        "job_type": null
    },
    {
        "Order": null,
        "job_id": 2,
        "op_id": 1,
        "machine_id": 1,
        "start_time": 93,
        "process_time": 84,
        "finish_time": 177,
        "job_type": null
    },
    {
        "Order": null,
        "job_id": 8,
        "op_id": 4,
        "machine_id": 1,
        "start_time": 192,
        "process_time": 30,
        "finish_time": 222,
        "job_type": null
    },
    {
        "Order": null,
        "job_id": 14,
        "op_id": 3,
        "machine_id": 1,
        "start_time": 276,
        "process_time": 38,
        "finish_time": 314,
        "job_type": null
    },
    {
        "Order": null,
        "job_id": 13,
        "op_id": 4,
        "machine_id": 1,
        "start_time": 358,
        "process_time": 83,
        "finish_time": 441,
        "job_type": null
    },
    {
        "Order": null,
        "job_id": 0,
        "op_id": 7,
        "machine_id": 1,
        "start_time": 487,
        "process_time": 29,
        "finish_time": 516,
        "job_type": null
    },
    {
        "Order": null,
        "job_id": 12,
        "op_id": 3,
        "machine_id": 1,
        "start_time": 561,
        "process_time": 39,
        "finish_time": 600,
        "job_type": null
    },
    {
        "Order": null,
        "job_id": 1,
        "op_id": 7,
        "machine_id": 1,
        "start_time": 612,
        "process_time": 80,
        "finish_time": 692,
        "job_type": null
    },
    {
        "Order": null,
        "job_id": 4,
        "op_id": 6,
        "machine_id": 1,
        "start_time": 700,
        "process_time": 48,
        "finish_time": 748,
        "job_type": null
    },
    {
        "Order": null,
        "job_id": 7,
        "op_id": 7,
        "machine_id": 1,
        "start_time": 748,
        "process_time": 33,
        "finish_time": 781,
        "job_type": null
    },
    {
        "Order": null,
        "job_id": 10,
        "op_id": 9,
        "machine_id": 1,
        "start_time": 781,
        "process_time": 84,
        "finish_time": 865,
        "job_type": null
    },
    {
        "Order": null,
        "job_id": 9,
        "op_id": 9,
        "machine_id": 1,
        "start_time": 865,
        "process_time": 49,
        "finish_time": 914,
        "job_type": null
    },
    {
        "Order": null,
        "job_id": 6,
        "op_id": 9,
        "machine_id": 1,
        "start_time": 914,
        "process_time": 7,
        "finish_time": 921,
        "job_type": null
    },
    {
        "Order": null,
        "job_id": 5,
        "op_id": 9,
        "machine_id": 1,
        "start_time": 921,
        "process_time": 56,
        "finish_time": 977,
        "job_type": null
    },
    {
        "Order": null,
        "job_id": 3,
        "op_id": 0,
        "machine_id": 2,
        "start_time": 0,
        "process_time": 42,
        "finish_time": 42,
        "job_type": null
    },
    {
        "Order": null,
        "job_id": 8,
        "op_id": 0,
        "machine_id": 2,
        "start_time": 42,
        "process_time": 44,
        "finish_time": 86,
        "job_type": null
    },
    {
        "Order": null,
        "job_id": 12,
        "op_id": 0,
        "machine_id": 2,
        "start_time": 86,
        "process_time": 15,
        "finish_time": 101,
        "job_type": null
    },
    {
        "Order": null,
        "job_id": 13,
        "op_id": 1,
        "machine_id": 2,
        "start_time": 101,
        "process_time": 92,
        "finish_time": 193,
        "job_type": null
    },
    {
        "Order": null,
        "job_id": 0,
        "op_id": 3,
        "machine_id": 2,
        "start_time": 193,
        "process_time": 38,
        "finish_time": 231,
        "job_type": null
    },
    {
        "Order": null,
        "job_id": 1,
        "op_id": 2,
        "machine_id": 2,
        "start_time": 231,
        "process_time": 85,
        "finish_time": 316,
        "job_type": null
    },
    {
        "Order": null,
        "job_id": 6,
        "op_id": 1,
        "machine_id": 2,
        "start_time": 316,
        "process_time": 64,
        "finish_time": 380,
        "job_type": null
    },
    {
        "Order": null,
        "job_id": 5,
        "op_id": 1,
        "machine_id": 2,
        "start_time": 380,
        "process_time": 72,
        "finish_time": 452,
        "job_type": null
    },
    {
        "Order": null,
        "job_id": 4,
        "op_id": 1,
        "machine_id": 2,
        "start_time": 452,
        "process_time": 70,
        "finish_time": 522,
        "job_type": null
    },
    {
        "Order": null,
        "job_id": 11,
        "op_id": 7,
        "machine_id": 2,
        "start_time": 522,
        "process_time": 17,
        "finish_time": 539,
        "job_type": null
    },
    {
        "Order": null,
        "job_id": 10,
        "op_id": 7,
        "machine_id": 2,
        "start_time": 539,
        "process_time": 77,
        "finish_time": 616,
        "job_type": null
    },
    {
        "Order": null,
        "job_id": 7,
        "op_id": 4,
        "machine_id": 2,
        "start_time": 616,
        "process_time": 65,
        "finish_time": 681,
        "job_type": null
    },
    {
        "Order": null,
        "job_id": 9,
        "op_id": 6,
        "machine_id": 2,
        "start_time": 681,
        "process_time": 28,
        "finish_time": 709,
        "job_type": null
    },
    {
        "Order": null,
        "job_id": 14,
        "op_id": 5,
        "machine_id": 2,
        "start_time": 709,
        "process_time": 69,
        "finish_time": 778,
        "job_type": null
    },
    {
        "Order": null,
        "job_id": 2,
        "op_id": 9,
        "machine_id": 2,
        "start_time": 917,
        "process_time": 14,
        "finish_time": 931,
        "job_type": null
    },
    {
        "Order": null,
        "job_id": 7,
        "op_id": 0,
        "machine_id": 3,
        "start_time": 0,
        "process_time": 86,
        "finish_time": 86,
        "job_type": null
    },
    {
        "Order": null,
        "job_id": 8,
        "op_id": 1,
        "machine_id": 3,
        "start_time": 87,
        "process_time": 16,
        "finish_time": 103,
        "job_type": null
    },
    {
        "Order": null,
        "job_id": 0,
        "op_id": 2,
        "machine_id": 3,
        "start_time": 103,
        "process_time": 12,
        "finish_time": 115,
        "job_type": null
    },
    {
        "Order": null,
        "job_id": 1,
        "op_id": 1,
        "machine_id": 3,
        "start_time": 115,
        "process_time": 82,
        "finish_time": 197,
        "job_type": null
    },
    {
        "Order": null,
        "job_id": 10,
        "op_id": 5,
        "machine_id": 3,
        "start_time": 229,
        "process_time": 34,
        "finish_time": 263,
        "job_type": null
    },
    {
        "Order": null,
        "job_id": 14,
        "op_id": 4,
        "machine_id": 3,
        "start_time": 314,
        "process_time": 91,
        "finish_time": 405,
        "job_type": null
    },
    {
        "Order": null,
        "job_id": 6,
        "op_id": 2,
        "machine_id": 3,
        "start_time": 405,
        "process_time": 78,
        "finish_time": 483,
        "job_type": null
    },
    {
        "Order": null,
        "job_id": 11,
        "op_id": 6,
        "machine_id": 3,
        "start_time": 483,
        "process_time": 29,
        "finish_time": 512,
        "job_type": null
    },
    {
        "Order": null,
        "job_id": 4,
        "op_id": 2,
        "machine_id": 3,
        "start_time": 523,
        "process_time": 75,
        "finish_time": 598,
        "job_type": null
    },
    {
        "Order": null,
        "job_id": 2,
        "op_id": 6,
        "machine_id": 3,
        "start_time": 599,
        "process_time": 41,
        "finish_time": 640,
        "job_type": null
    },
    {
        "Order": null,
        "job_id": 5,
        "op_id": 5,
        "machine_id": 3,
        "start_time": 643,
        "process_time": 95,
        "finish_time": 738,
        "job_type": null
    },
    {
        "Order": null,
        "job_id": 12,
        "op_id": 7,
        "machine_id": 3,
        "start_time": 738,
        "process_time": 32,
        "finish_time": 770,
        "job_type": null
    },
    {
        "Order": null,
        "job_id": 3,
        "op_id": 8,
        "machine_id": 3,
        "start_time": 770,
        "process_time": 74,
        "finish_time": 844,
        "job_type": null
    },
    {
        "Order": null,
        "job_id": 9,
        "op_id": 8,
        "machine_id": 3,
        "start_time": 844,
        "process_time": 20,
        "finish_time": 864,
        "job_type": null
    },
    {
        "Order": null,
        "job_id": 13,
        "op_id": 8,
        "machine_id": 3,
        "start_time": 864,
        "process_time": 99,
        "finish_time": 963,
        "job_type": null
    },
    {
        "Order": null,
        "job_id": 0,
        "op_id": 1,
        "machine_id": 4,
        "start_time": 14,
        "process_time": 75,
        "finish_time": 89,
        "job_type": null
    },
    {
        "Order": null,
        "job_id": 8,
        "op_id": 2,
        "machine_id": 4,
        "start_time": 103,
        "process_time": 11,
        "finish_time": 114,
        "job_type": null
    },
    {
        "Order": null,
        "job_id": 14,
        "op_id": 0,
        "machine_id": 4,
        "start_time": 114,
        "process_time": 88,
        "finish_time": 202,
        "job_type": null
    },
    {
        "Order": null,
        "job_id": 10,
        "op_id": 3,
        "machine_id": 4,
        "start_time": 202,
        "process_time": 10,
        "finish_time": 212,
        "job_type": null
    },
    {
        "Order": null,
        "job_id": 3,
        "op_id": 4,
        "machine_id": 4,
        "start_time": 212,
        "process_time": 59,
        "finish_time": 271,
        "job_type": null
    },
    {
        "Order": null,
        "job_id": 1,
        "op_id": 3,
        "machine_id": 4,
        "start_time": 316,
        "process_time": 58,
        "finish_time": 374,
        "job_type": null
    },
    {
        "Order": null,
        "job_id": 2,
        "op_id": 4,
        "machine_id": 4,
        "start_time": 374,
        "process_time": 8,
        "finish_time": 382,
        "job_type": null
    },
    {
        "Order": null,
        "job_id": 11,
        "op_id": 4,
        "machine_id": 4,
        "start_time": 382,
        "process_time": 76,
        "finish_time": 458,
        "job_type": null
    },
    {
        "Order": null,
        "job_id": 9,
        "op_id": 2,
        "machine_id": 4,
        "start_time": 458,
        "process_time": 47,
        "finish_time": 505,
        "job_type": null
    },
    {
        "Order": null,
        "job_id": 6,
        "op_id": 4,
        "machine_id": 4,
        "start_time": 505,
        "process_time": 94,
        "finish_time": 599,
        "job_type": null
    },
    {
        "Order": null,
        "job_id": 12,
        "op_id": 4,
        "machine_id": 4,
        "start_time": 600,
        "process_time": 39,
        "finish_time": 639,
        "job_type": null
    },
    {
        "Order": null,
        "job_id": 4,
        "op_id": 4,
        "machine_id": 4,
        "start_time": 640,
        "process_time": 37,
        "finish_time": 677,
        "job_type": null
    },
    {
        "Order": null,
        "job_id": 7,
        "op_id": 5,
        "machine_id": 4,
        "start_time": 681,
        "process_time": 30,
        "finish_time": 711,
        "job_type": null
    },
    {
        "Order": null,
        "job_id": 5,
        "op_id": 6,
        "machine_id": 4,
        "start_time": 738,
        "process_time": 25,
        "finish_time": 763,
        "job_type": null
    },
    {
        "Order": null,
        "job_id": 13,
        "op_id": 7,
        "machine_id": 4,
        "start_time": 768,
        "process_time": 91,
        "finish_time": 859,
        "job_type": null
    },
    {
        "Order": null,
        "job_id": 1,
        "op_id": 0,
        "machine_id": 5,
        "start_time": 0,
        "process_time": 38,
        "finish_time": 38,
        "job_type": null
    },
    {
        "Order": null,
        "job_id": 11,
        "op_id": 1,
        "machine_id": 5,
        "start_time": 85,
        "process_time": 7,
        "finish_time": 92,
        "job_type": null
    },
    {
        "Order": null,
        "job_id": 3,
        "op_id": 3,
        "machine_id": 5,
        "start_time": 193,
        "process_time": 19,
        "finish_time": 212,
        "job_type": null
    },
    {
        "Order": null,
        "job_id": 10,
        "op_id": 4,
        "machine_id": 5,
        "start_time": 212,
        "process_time": 17,
        "finish_time": 229,
        "job_type": null
    },
    {
        "Order": null,
        "job_id": 13,
        "op_id": 2,
        "machine_id": 5,
        "start_time": 229,
        "process_time": 33,
        "finish_time": 262,
        "job_type": null
    },
    {
        "Order": null,
        "job_id": 0,
        "op_id": 5,
        "machine_id": 5,
        "start_time": 312,
        "process_time": 97,
        "finish_time": 409,
        "job_type": null
    },
    {
        "Order": null,
        "job_id": 6,
        "op_id": 3,
        "machine_id": 5,
        "start_time": 483,
        "process_time": 21,
        "finish_time": 504,
        "job_type": null
    },
    {
        "Order": null,
        "job_id": 5,
        "op_id": 4,
        "machine_id": 5,
        "start_time": 569,
        "process_time": 73,
        "finish_time": 642,
        "job_type": null
    },
    {
        "Order": null,
        "job_id": 9,
        "op_id": 5,
        "machine_id": 5,
        "start_time": 644,
        "process_time": 11,
        "finish_time": 655,
        "job_type": null
    },
    {
        "Order": null,
        "job_id": 2,
        "op_id": 7,
        "machine_id": 5,
        "start_time": 655,
        "process_time": 61,
        "finish_time": 716,
        "job_type": null
    },
    {
        "Order": null,
        "job_id": 7,
        "op_id": 6,
        "machine_id": 5,
        "start_time": 716,
        "process_time": 32,
        "finish_time": 748,
        "job_type": null
    },
    {
        "Order": null,
        "job_id": 4,
        "op_id": 7,
        "machine_id": 5,
        "start_time": 800,
        "process_time": 5,
        "finish_time": 805,
        "job_type": null
    },
    {
        "Order": null,
        "job_id": 8,
        "op_id": 8,
        "machine_id": 5,
        "start_time": 805,
        "process_time": 61,
        "finish_time": 866,
        "job_type": null
    },
    {
        "Order": null,
        "job_id": 14,
        "op_id": 8,
        "machine_id": 5,
        "start_time": 866,
        "process_time": 39,
        "finish_time": 905,
        "job_type": null
    },
    {
        "Order": null,
        "job_id": 12,
        "op_id": 9,
        "machine_id": 5,
        "start_time": 905,
        "process_time": 64,
        "finish_time": 969,
        "job_type": null
    },
    {
        "Order": null,
        "job_id": 13,
        "op_id": 0,
        "machine_id": 6,
        "start_time": 0,
        "process_time": 32,
        "finish_time": 32,
        "job_type": null
    },
    {
        "Order": null,
        "job_id": 10,
        "op_id": 1,
        "machine_id": 6,
        "start_time": 34,
        "process_time": 49,
        "finish_time": 83,
        "job_type": null
    },
    {
        "Order": null,
        "job_id": 4,
        "op_id": 0,
        "machine_id": 6,
        "start_time": 83,
        "process_time": 55,
        "finish_time": 138,
        "job_type": null
    },
    {
        "Order": null,
        "job_id": 8,
        "op_id": 3,
        "machine_id": 6,
        "start_time": 147,
        "process_time": 45,
        "finish_time": 192,
        "job_type": null
    },
    {
        "Order": null,
        "job_id": 11,
        "op_id": 3,
        "machine_id": 6,
        "start_time": 192,
        "process_time": 59,
        "finish_time": 251,
        "job_type": null
    },
    {
        "Order": null,
        "job_id": 2,
        "op_id": 3,
        "machine_id": 6,
        "start_time": 269,
        "process_time": 48,
        "finish_time": 317,
        "job_type": null
    },
    {
        "Order": null,
        "job_id": 1,
        "op_id": 4,
        "machine_id": 6,
        "start_time": 374,
        "process_time": 87,
        "finish_time": 461,
        "job_type": null
    },
    {
        "Order": null,
        "job_id": 12,
        "op_id": 1,
        "machine_id": 6,
        "start_time": 461,
        "process_time": 87,
        "finish_time": 548,
        "job_type": null
    },
    {
        "Order": null,
        "job_id": 9,
        "op_id": 3,
        "machine_id": 6,
        "start_time": 548,
        "process_time": 52,
        "finish_time": 600,
        "job_type": null
    },
    {
        "Order": null,
        "job_id": 0,
        "op_id": 9,
        "machine_id": 6,
        "start_time": 679,
        "process_time": 66,
        "finish_time": 745,
        "job_type": null
    },
    {
        "Order": null,
        "job_id": 6,
        "op_id": 7,
        "machine_id": 6,
        "start_time": 757,
        "process_time": 16,
        "finish_time": 773,
        "job_type": null
    },
    {
        "Order": null,
        "job_id": 14,
        "op_id": 6,
        "machine_id": 6,
        "start_time": 778,
        "process_time": 21,
        "finish_time": 799,
        "job_type": null
    },
    {
        "Order": null,
        "job_id": 5,
        "op_id": 7,
        "machine_id": 6,
        "start_time": 799,
        "process_time": 43,
        "finish_time": 842,
        "job_type": null
    },
    {
        "Order": null,
        "job_id": 3,
        "op_id": 9,
        "machine_id": 6,
        "start_time": 865,
        "process_time": 41,
        "finish_time": 906,
        "job_type": null
    },
    {
        "Order": null,
        "job_id": 7,
        "op_id": 9,
        "machine_id": 6,
        "start_time": 906,
        "process_time": 59,
        "finish_time": 965,
        "job_type": null
    },
    {
        "Order": null,
        "job_id": 9,
        "op_id": 0,
        "machine_id": 7,
        "start_time": 0,
        "process_time": 36,
        "finish_time": 36,
        "job_type": null
    },
    {
        "Order": null,
        "job_id": 10,
        "op_id": 2,
        "machine_id": 7,
        "start_time": 83,
        "process_time": 74,
        "finish_time": 157,
        "job_type": null
    },
    {
        "Order": null,
        "job_id": 7,
        "op_id": 1,
        "machine_id": 7,
        "start_time": 157,
        "process_time": 85,
        "finish_time": 242,
        "job_type": null
    },
    {
        "Order": null,
        "job_id": 14,
        "op_id": 1,
        "machine_id": 7,
        "start_time": 242,
        "process_time": 7,
        "finish_time": 249,
        "job_type": null
    },
    {
        "Order": null,
        "job_id": 3,
        "op_id": 5,
        "machine_id": 7,
        "start_time": 274,
        "process_time": 97,
        "finish_time": 371,
        "job_type": null
    },
    {
        "Order": null,
        "job_id": 2,
        "op_id": 5,
        "machine_id": 7,
        "start_time": 382,
        "process_time": 7,
        "finish_time": 389,
        "job_type": null
    },
    {
        "Order": null,
        "job_id": 5,
        "op_id": 2,
        "machine_id": 7,
        "start_time": 459,
        "process_time": 31,
        "finish_time": 490,
        "job_type": null
    },
    {
        "Order": null,
        "job_id": 13,
        "op_id": 5,
        "machine_id": 7,
        "start_time": 491,
        "process_time": 57,
        "finish_time": 548,
        "job_type": null
    },
    {
        "Order": null,
        "job_id": 12,
        "op_id": 2,
        "machine_id": 7,
        "start_time": 550,
        "process_time": 11,
        "finish_time": 561,
        "job_type": null
    },
    {
        "Order": null,
        "job_id": 0,
        "op_id": 8,
        "machine_id": 7,
        "start_time": 561,
        "process_time": 44,
        "finish_time": 605,
        "job_type": null
    },
    {
        "Order": null,
        "job_id": 11,
        "op_id": 8,
        "machine_id": 7,
        "start_time": 605,
        "process_time": 48,
        "finish_time": 653,
        "job_type": null
    },
    {
        "Order": null,
        "job_id": 4,
        "op_id": 5,
        "machine_id": 7,
        "start_time": 677,
        "process_time": 23,
        "finish_time": 700,
        "job_type": null
    },
    {
        "Order": null,
        "job_id": 1,
        "op_id": 8,
        "machine_id": 7,
        "start_time": 700,
        "process_time": 69,
        "finish_time": 769,
        "job_type": null
    },
    {
        "Order": null,
        "job_id": 6,
        "op_id": 8,
        "machine_id": 7,
        "start_time": 799,
        "process_time": 86,
        "finish_time": 885,
        "job_type": null
    },
    {
        "Order": null,
        "job_id": 8,
        "op_id": 9,
        "machine_id": 7,
        "start_time": 885,
        "process_time": 90,
        "finish_time": 975,
        "job_type": null
    },
    {
        "Order": null,
        "job_id": 0,
        "op_id": 0,
        "machine_id": 8,
        "start_time": 0,
        "process_time": 14,
        "finish_time": 14,
        "job_type": null
    },
    {
        "Order": null,
        "job_id": 10,
        "op_id": 0,
        "machine_id": 8,
        "start_time": 14,
        "process_time": 20,
        "finish_time": 34,
        "job_type": null
    },
    {
        "Order": null,
        "job_id": 5,
        "op_id": 0,
        "machine_id": 8,
        "start_time": 34,
        "process_time": 9,
        "finish_time": 43,
        "job_type": null
    },
    {
        "Order": null,
        "job_id": 9,
        "op_id": 1,
        "machine_id": 8,
        "start_time": 43,
        "process_time": 31,
        "finish_time": 74,
        "job_type": null
    },
    {
        "Order": null,
        "job_id": 11,
        "op_id": 2,
        "machine_id": 8,
        "start_time": 92,
        "process_time": 71,
        "finish_time": 163,
        "job_type": null
    },
    {
        "Order": null,
        "job_id": 14,
        "op_id": 2,
        "machine_id": 8,
        "start_time": 249,
        "process_time": 27,
        "finish_time": 276,
        "job_type": null
    },
    {
        "Order": null,
        "job_id": 13,
        "op_id": 3,
        "machine_id": 8,
        "start_time": 276,
        "process_time": 82,
        "finish_time": 358,
        "job_type": null
    },
    {
        "Order": null,
        "job_id": 8,
        "op_id": 6,
        "machine_id": 8,
        "start_time": 383,
        "process_time": 93,
        "finish_time": 476,
        "job_type": null
    },
    {
        "Order": null,
        "job_id": 3,
        "op_id": 7,
        "machine_id": 8,
        "start_time": 516,
        "process_time": 43,
        "finish_time": 559,
        "job_type": null
    },
    {
        "Order": null,
        "job_id": 4,
        "op_id": 3,
        "machine_id": 8,
        "start_time": 598,
        "process_time": 42,
        "finish_time": 640,
        "job_type": null
    },
    {
        "Order": null,
        "job_id": 12,
        "op_id": 5,
        "machine_id": 8,
        "start_time": 640,
        "process_time": 43,
        "finish_time": 683,
        "job_type": null
    },
    {
        "Order": null,
        "job_id": 6,
        "op_id": 6,
        "machine_id": 8,
        "start_time": 683,
        "process_time": 53,
        "finish_time": 736,
        "job_type": null
    },
    {
        "Order": null,
        "job_id": 2,
        "op_id": 8,
        "machine_id": 8,
        "start_time": 773,
        "process_time": 66,
        "finish_time": 839,
        "job_type": null
    },
    {
        "Order": null,
        "job_id": 7,
        "op_id": 8,
        "machine_id": 8,
        "start_time": 839,
        "process_time": 44,
        "finish_time": 883,
        "job_type": null
    },
    {
        "Order": null,
        "job_id": 1,
        "op_id": 9,
        "machine_id": 8,
        "start_time": 883,
        "process_time": 92,
        "finish_time": 975,
        "job_type": null
    },
    {
        "Order": null,
        "job_id": 2,
        "op_id": 0,
        "machine_id": 9,
        "start_time": 0,
        "process_time": 5,
        "finish_time": 5,
        "job_type": null
    },
    {
        "Order": null,
        "job_id": 8,
        "op_id": 5,
        "machine_id": 9,
        "start_time": 222,
        "process_time": 84,
        "finish_time": 306,
        "job_type": null
    },
    {
        "Order": null,
        "job_id": 7,
        "op_id": 2,
        "machine_id": 9,
        "start_time": 306,
        "process_time": 63,
        "finish_time": 369,
        "job_type": null
    },
    {
        "Order": null,
        "job_id": 3,
        "op_id": 6,
        "machine_id": 9,
        "start_time": 371,
        "process_time": 73,
        "finish_time": 444,
        "job_type": null
    },
    {
        "Order": null,
        "job_id": 0,
        "op_id": 6,
        "machine_id": 9,
        "start_time": 444,
        "process_time": 12,
        "finish_time": 456,
        "job_type": null
    },
    {
        "Order": null,
        "job_id": 1,
        "op_id": 5,
        "machine_id": 9,
        "start_time": 461,
        "process_time": 89,
        "finish_time": 550,
        "job_type": null
    },
    {
        "Order": null,
        "job_id": 13,
        "op_id": 6,
        "machine_id": 9,
        "start_time": 550,
        "process_time": 99,
        "finish_time": 649,
        "job_type": null
    },
    {
        "Order": null,
        "job_id": 6,
        "op_id": 5,
        "machine_id": 9,
        "start_time": 649,
        "process_time": 31,
        "finish_time": 680,
        "job_type": null
    },
    {
        "Order": null,
        "job_id": 10,
        "op_id": 8,
        "machine_id": 9,
        "start_time": 680,
        "process_time": 68,
        "finish_time": 748,
        "job_type": null
    },
    {
        "Order": null,
        "job_id": 9,
        "op_id": 7,
        "machine_id": 9,
        "start_time": 748,
        "process_time": 35,
        "finish_time": 783,
        "job_type": null
    },
    {
        "Order": null,
        "job_id": 12,
        "op_id": 8,
        "machine_id": 9,
        "start_time": 783,
        "process_time": 16,
        "finish_time": 799,
        "job_type": null
    },
    {
        "Order": null,
        "job_id": 14,
        "op_id": 7,
        "machine_id": 9,
        "start_time": 799,
        "process_time": 62,
        "finish_time": 861,
        "job_type": null
    },
    {
        "Order": null,
        "job_id": 5,
        "op_id": 8,
        "machine_id": 9,
        "start_time": 861,
        "process_time": 60,
        "finish_time": 921,
        "job_type": null
    },
    {
        "Order": null,
        "job_id": 4,
        "op_id": 8,
        "machine_id": 9,
        "start_time": 921,
        "process_time": 38,
        "finish_time": 959,
        "job_type": null
    },
    {
        "Order": null,
        "job_id": 11,
        "op_id": 9,
        "machine_id": 9,
        "start_time": 959,
        "process_time": 13,
        "finish_time": 972,
        "job_type": null
    }
]